{
  "model": {
    "id": "johnson-controls-nae55",
    "brand": "johnson-controls",
    "type": "supervisory-controllers",
    "name": "NAE55",
    "slug": "nae55",
    "model_numbers": ["NAE5510", "NAE5520"],
    "protocols": ["BACnet/IP", "BACnet MS/TP", "N2"],
    "status": "current",
    "description": "Network automation engine providing supervisory control, scheduling, and alarming for Metasys field devices.",
    "manufacturer_url": "https://www.johnsoncontrols.com",
    "image_url": "",
    "added_at": "2026-03-16"
  }
}
